TensorflowKuaisuRumenjiaochengCYuyanZhongwenwang/README.md
TensorflowKuaisuRumenjiaochengCYuyanZhongwenwang/__init__.py
TensorflowKuaisuRumenjiaochengCYuyanZhongwenwang/__main__.py
TensorflowKuaisuRumenjiaochengCYuyanZhongwenwang/file.epub
TensorflowKuaisuRumenjiaochengCYuyanZhongwenwang/index.html
TensorflowKuaisuRumenjiaochengCYuyanZhongwenwang/css/__init__.py
TensorflowKuaisuRumenjiaochengCYuyanZhongwenwang/css/annotations.css
TensorflowKuaisuRumenjiaochengCYuyanZhongwenwang/css/main.css
TensorflowKuaisuRumenjiaochengCYuyanZhongwenwang/css/normalize.css
TensorflowKuaisuRumenjiaochengCYuyanZhongwenwang/css/popup.css
TensorflowKuaisuRumenjiaochengCYuyanZhongwenwang/font/__init__.py
TensorflowKuaisuRumenjiaochengCYuyanZhongwenwang/font/fontello.eot
TensorflowKuaisuRumenjiaochengCYuyanZhongwenwang/font/fontello.svg
TensorflowKuaisuRumenjiaochengCYuyanZhongwenwang/font/fontello.ttf
TensorflowKuaisuRumenjiaochengCYuyanZhongwenwang/font/fontello.woff
TensorflowKuaisuRumenjiaochengCYuyanZhongwenwang/img/__init__.py
TensorflowKuaisuRumenjiaochengCYuyanZhongwenwang/img/annotator-glyph-sprite.png
TensorflowKuaisuRumenjiaochengCYuyanZhongwenwang/img/annotator-icon-sprite.png
TensorflowKuaisuRumenjiaochengCYuyanZhongwenwang/img/apple-touch-icon.png
TensorflowKuaisuRumenjiaochengCYuyanZhongwenwang/img/cancelfullscreen.png
TensorflowKuaisuRumenjiaochengCYuyanZhongwenwang/img/close.png
TensorflowKuaisuRumenjiaochengCYuyanZhongwenwang/img/fullscreen.png
TensorflowKuaisuRumenjiaochengCYuyanZhongwenwang/img/loader.gif
TensorflowKuaisuRumenjiaochengCYuyanZhongwenwang/img/menu-icon.png
TensorflowKuaisuRumenjiaochengCYuyanZhongwenwang/img/save.png
TensorflowKuaisuRumenjiaochengCYuyanZhongwenwang/img/saved.png
TensorflowKuaisuRumenjiaochengCYuyanZhongwenwang/img/settings-s.png
TensorflowKuaisuRumenjiaochengCYuyanZhongwenwang/img/settings.png
TensorflowKuaisuRumenjiaochengCYuyanZhongwenwang/img/star.png
TensorflowKuaisuRumenjiaochengCYuyanZhongwenwang/js/__init__.py
tensorflow_kuaisu_rumenjiaocheng_c_yuyan_zhongwenwang-2024.3.5.0.dist-info/METADATA
tensorflow_kuaisu_rumenjiaocheng_c_yuyan_zhongwenwang-2024.3.5.0.dist-info/WHEEL
tensorflow_kuaisu_rumenjiaocheng_c_yuyan_zhongwenwang-2024.3.5.0.dist-info/entry_points.txt
tensorflow_kuaisu_rumenjiaocheng_c_yuyan_zhongwenwang-2024.3.5.0.dist-info/top_level.txt
tensorflow_kuaisu_rumenjiaocheng_c_yuyan_zhongwenwang-2024.3.5.0.dist-info/RECORD
